ciw/__init__.py
ciw/arrival_node.py
ciw/auxiliary.py
ciw/data_record.py
ciw/disciplines.py
ciw/exactnode.py
ciw/exit_node.py
ciw/import_params.py
ciw/individual.py
ciw/network.py
ciw/node.py
ciw/processor_sharing.py
ciw/schedules.py
ciw/server.py
ciw/simulation.py
ciw/version.py
ciw/deadlock/__init__.py
ciw/deadlock/deadlock_detector.py
ciw/dists/__init__.py
ciw/dists/distributions.py
ciw/routing/__init__.py
ciw/routing/routing.py
ciw/trackers/__init__.py
ciw/trackers/state_tracker.py
ciw-3.2.7.dist-info/licenses/AUTHORS.rst
ciw-3.2.7.dist-info/licenses/LICENSE.txt
tests/__init__.py
tests/test_arrival_node.py
tests/test_auxiliary.py
tests/test_data_record.py
tests/test_exit_node.py
tests/test_individual.py
tests/test_network.py
tests/test_node.py
tests/test_process_based.py
tests/test_processor_sharing.py
tests/test_routing.py
tests/test_sampling.py
tests/test_scheduling.py
tests/test_server.py
tests/test_simulation.py
tests/test_state_tracker.py
tests/test_version.py
ciw-3.2.7.dist-info/METADATA
ciw-3.2.7.dist-info/WHEEL
ciw-3.2.7.dist-info/top_level.txt
ciw-3.2.7.dist-info/RECORD
