Metadata-Version: 2.4
Name: Ciw
Version: 3.2.7
Summary: A discrete event simulation library for open queueing networks
Home-page: https://github.com/CiwPython/Ciw
Author: Geraint Palmer, Vincent Knight
Author-email: palmer.geraint@googlemail.com
License-File: LICENSE.txt
License-File: AUTHORS.rst
Requires-Dist: setuptools>=69
Requires-Dist: networkx>=2.3
Requires-Dist: tqdm>=4.66.3
Requires-Dist: numpy>=1.21.6
Dynamic: author
Dynamic: author-email
Dynamic: description
Dynamic: home-page
Dynamic: license-file
Dynamic: requires-dist
Dynamic: summary
